verilator/ex2/encode42/vsrc/encode42.v
module encode42(
	input en,
	input [3:0]x,
	output reg[1:0]y
);
always@(*)begin
	if(!en) y=2'b00;
	else begin
		casez(x)
			4'b1???:y=2'b11;
			4'b01??:y=2'b10;
			4'b001?:y=2'b01;
			4'b0001:y=2'b00;
			default:y=2'b00;
		endcase
	end
end
endmodule

verilator/ex2/encode42/encode42.vcd
$version Generated by VerilatedVcd $end
$timescale 1s $end
 $scope module TOP $end
  $var wire 1 # en $end
  $var wire 4 $ x [3:0] $end
  $var wire 2 % y [1:0] $end
  $scope module encode42 $end
   $var wire 1 # en $end
   $var wire 4 $ x [3:0] $end
   $var wire 2 % y [1:0] $end
  $upscope $end
 $upscope $end
$enddefinitions $end


#1
0#
b0000 $
b00 %
#2
b0001 $
#3
b0010 $
#4
b0100 $
#5
b1000 $
#6
1#
b0000 $
#7
b0001 $
#8
b0010 $
b01 %
#9
b0100 $
b10 %
#10
b1000 $
b11 %
#11
0#
b00 %
